<?xml version="1.0" encoding="utf-8"?>
<Patch>


  <!-- teardrop earrings -->
  <Operation Class="PatchOperationReplace">
    <xpath>Defs/ThingDef[defName="Apparel_PAETeardropEarrings"]/label</xpath>
    <value>
      <label>teardrop earrings</label>
    </value>
  </Operation>

  <!-- rod earrings -->
  <Operation Class="PatchOperationReplace">
    <xpath>Defs/ThingDef[defName="Apparel_PAERodEarrings"]/label</xpath>
    <value>
      <label>rod earrings</label>
    </value>
  </Operation>

  <!-- small earrings -->
  <Operation Class="PatchOperationReplace">
    <xpath>Defs/ThingDef[defName="Apparel_PAESmallEarrings"]/label</xpath>
    <value>
      <label>small earrings</label>
    </value>
  </Operation>

  <!-- orange sunglasses -->
  <Operation Class="PatchOperationReplace">
    <xpath>Defs/ThingDef[defName="Apparel_PAGSunglassesA"]/label</xpath>
    <value>
      <label>orange sunglasses</label>
    </value>
  </Operation>

  <!-- sunglasses -->
  <Operation Class="PatchOperationReplace">
    <xpath>Defs/ThingDef[defName="Apparel_PAGSunglassesB"]/label</xpath>
    <value>
      <label>sunglasses</label>
    </value>
  </Operation>

  <!-- glasses -->
  <Operation Class="PatchOperationReplace">
    <xpath>Defs/ThingDef[defName="Apparel_PAGGlasses"]/label</xpath>
    <value>
      <label>glasses</label>
    </value>
  </Operation>

  <!-- eyepatch left (over hair) -->
  <Operation Class="PatchOperationReplace">
    <xpath>Defs/ThingDef[defName="Apparel_PAGEyepatchL"]/label</xpath>
    <value>
      <label>left eyepatch (over hair)</label>
    </value>
  </Operation>

  <!-- eyepatch right (over hair) -->
  <Operation Class="PatchOperationReplace">
    <xpath>Defs/ThingDef[defName="Apparel_PAGEyepatchR"]/label</xpath>
    <value>
      <label>right eyepatch (over hair)</label>
    </value>
  </Operation>

  <!-- eyepatch left (under hair) -->
  <Operation Class="PatchOperationReplace">
    <xpath>Defs/ThingDef[defName="Apparel_PAGEyepatchLU"]/label</xpath>
    <value>
      <label>left eyepatch (under hair)</label>
    </value>
  </Operation>

  <!-- eyepatch right (under hair) -->
  <Operation Class="PatchOperationReplace">
    <xpath>Defs/ThingDef[defName="Apparel_PAGEyepatchRU"]/label</xpath>
    <value>
      <label>right eyepatch (under hair)</label>
    </value>
  </Operation>


  <!-- hair scarf -->
  <Operation Class="PatchOperationReplace">
    <xpath>Defs/ThingDef[defName="Apparel_PAHHeadScarf"]/label</xpath>
    <value>
      <label>hair scarf</label>
    </value>
  </Operation>

  <!-- hair scarf with lace -->
  <Operation Class="PatchOperationReplace">
    <xpath>Defs/ThingDef[defName="Apparel_PAHHeadScarfB"]/label</xpath>
    <value>
      <label>hair scarf with lace</label>
    </value>
  </Operation>

  <!-- simple headband -->
  <Operation Class="PatchOperationReplace">
    <xpath>Defs/ThingDef[defName="Apparel_PAHHeadband"]/label</xpath>
    <value>
      <label>simple headband</label>
    </value>
  </Operation>

  <!-- ribbon headband -->
  <Operation Class="PatchOperationReplace">
    <xpath>Defs/ThingDef[defName="Apparel_PAHRibbonHeadband"]/label</xpath>
    <value>
      <label>ribbon headband</label>
    </value>
  </Operation>

  <!-- big ribbon -->
  <Operation Class="PatchOperationReplace">
    <xpath>Defs/ThingDef[defName="Apparel_PAHDekaRibbon"]/label</xpath>
    <value>
      <label>big ribbon</label>
    </value>
  </Operation>

  <!-- fluffy ribbon headband -->
  <Operation Class="PatchOperationReplace">
    <xpath>Defs/ThingDef[defName="Apparel_PAHMokoRibbon"]/label</xpath>
    <value>
      <label>fluffy ribbon headband</label>
    </value>
  </Operation>

  <!-- headphones -->
  <Operation Class="PatchOperationReplace">
    <xpath>Defs/ThingDef[defName="Apparel_PAHHeadphones"]/label</xpath>
    <value>
      <label>headphones</label>
    </value>
  </Operation>

  <!-- veil -->
  <Operation Class="PatchOperationReplace">
    <xpath>Defs/ThingDef[defName="Apparel_PAHVeil"]/label</xpath>
    <value>
      <label>veil</label>
    </value>
  </Operation>

  <!-- deep hood -->
  <Operation Class="PatchOperationReplace">
    <xpath>Defs/ThingDef[defName="Apparel_PAHDeepHood"]/label</xpath>
    <value>
      <label>deep hood</label>
    </value>
  </Operation>

  <!-- pilot goggles -->
  <Operation Class="PatchOperationReplace">
    <xpath>Defs/ThingDef[defName="Apparel_PAHPilotGoggles"]/label</xpath>
    <value>
      <label>pilot goggles</label>
    </value>
  </Operation>

  <!-- headdress -->
  <Operation Class="PatchOperationReplace">
    <xpath>Defs/ThingDef[defName="Apparel_PAHHeaddress"]/label</xpath>
    <value>
      <label>headdress</label>
    </value>
  </Operation>

  <!-- angola beret -->
  <Operation Class="PatchOperationReplace">
    <xpath>Defs/ThingDef[defName="Apparel_PAHAngolaBeret"]/label</xpath>
    <value>
      <label>angola beret</label>
    </value>
  </Operation>

  <!-- tiara -->
  <Operation Class="PatchOperationReplace">
    <xpath>Defs/ThingDef[defName="Apparel_PAHTiara"]/label</xpath>
    <value>
      <label>tiara</label>
    </value>
  </Operation>

  <!-- knit headband -->
  <Operation Class="PatchOperationReplace">
    <xpath>Defs/ThingDef[defName="Apparel_PAHKnitHeadband"]/label</xpath>
    <value>
      <label>knit headband</label>
    </value>
  </Operation>

  <!-- pillbox hat -->
  <Operation Class="PatchOperationReplace">
    <xpath>Defs/ThingDef[defName="Apparel_PAHPillboxHat"]/label</xpath>
    <value>
      <label>pillbox hat</label>
    </value>
  </Operation>

  <!-- fedora -->
  <Operation Class="PatchOperationReplace">
    <xpath>Defs/ThingDef[defName="Apparel_PAHFedora"]/label</xpath>
    <value>
      <label>fedora</label>
    </value>
  </Operation>

  <!-- flat cap -->
  <Operation Class="PatchOperationReplace">
    <xpath>Defs/ThingDef[defName="Apparel_PAHFlatCap"]/label</xpath>
    <value>
      <label>flat cap</label>
    </value>
  </Operation>

  <!-- cat ear newsboy -->
  <Operation Class="PatchOperationReplace">
    <xpath>Defs/ThingDef[defName="Apparel_PAHCatEarNewsboy"]/label</xpath>
    <value>
      <label>cat ear newsboy</label>
    </value>
  </Operation>

  <!-- sailor beret -->
  <Operation Class="PatchOperationReplace">
    <xpath>Defs/ThingDef[defName="Apparel_PAHSailorBeret"]/label</xpath>
    <value>
      <label>sailor beret</label>
    </value>
  </Operation>

  <!-- mecha bunny ears -->
  <Operation Class="PatchOperationReplace">
    <xpath>Defs/ThingDef[defName="Apparel_PAHMechaBunnyEars"]/label</xpath>
    <value>
      <label>mecha bunny ears</label>
    </value>
  </Operation>

  <!-- half kitsune mask -->
  <Operation Class="PatchOperationReplace">
    <xpath>Defs/ThingDef[defName="Apparel_PAHHalfKitsuneMask"]/label</xpath>
    <value>
      <label>half kitsune mask</label>
    </value>
  </Operation>

  <!-- cyber sun visor -->
  <Operation Class="PatchOperationReplace">
    <xpath>Defs/ThingDef[defName="Apparel_PAHCyberSunVisor"]/label</xpath>
    <value>
      <label>cyber sun visor</label>
    </value>
  </Operation>

  <!-- cyber helm -->
  <Operation Class="PatchOperationReplace">
    <xpath>Defs/ThingDef[defName="Apparel_PAHCyberHelm"]/label</xpath>
    <value>
      <label>cyber helm</label>
    </value>
  </Operation>


  <!-- hair extensions -->
  <Operation Class="PatchOperationReplace">
    <xpath>Defs/ThingDef[defName="Apparel_PAMHairExtensions"]/label</xpath>
    <value>
      <label>hair extensions</label>
    </value>
  </Operation>

  <!-- ribbon pin -->
  <Operation Class="PatchOperationReplace">
    <xpath>Defs/ThingDef[defName="Apparel_PAMRibbonPin"]/label</xpath>
    <value>
      <label>ribbon pin</label>
    </value>
  </Operation>

  <!-- star hair pin -->
  <Operation Class="PatchOperationReplace">
    <xpath>Defs/ThingDef[defName="Apparel_PAMStarHairPin"]/label</xpath>
    <value>
      <label>star hair pin</label>
    </value>
  </Operation>

  <!-- clover crown -->
  <Operation Class="PatchOperationReplace">
    <xpath>Defs/ThingDef[defName="Apparel_PAMCloverCrown"]/label</xpath>
    <value>
      <label>clover crown</label>
    </value>
  </Operation>

  <!-- floral pin -->
  <Operation Class="PatchOperationReplace">
    <xpath>Defs/ThingDef[defName="Apparel_PAMFloralPin"]/label</xpath>
    <value>
      <label>floral pin</label>
    </value>
  </Operation>

  <!-- rose crown -->
  <Operation Class="PatchOperationReplace">
    <xpath>Defs/ThingDef[defName="Apparel_PAMRoseCrown"]/label</xpath>
    <value>
      <label>rose crown</label>
    </value>
  </Operation>

  <!-- party hat -->
  <Operation Class="PatchOperationReplace">
    <xpath>Defs/ThingDef[defName="Apparel_PAMPartyHat"]/label</xpath>
    <value>
      <label>party hat</label>
    </value>
  </Operation>


  <!-- muffler -->
  <Operation Class="PatchOperationReplace">
    <xpath>Defs/ThingDef[defName="Apparel_PANMuffler"]/label</xpath>
    <value>
      <label>muffler</label>
    </value>
  </Operation>

  <!-- neck scarf -->
  <Operation Class="PatchOperationReplace">
    <xpath>Defs/ThingDef[defName="Apparel_PANNeckScarf"]/label</xpath>
    <value>
      <label>neck scarf</label>
    </value>
  </Operation>

  <!-- fluffy muffler -->
  <Operation Class="PatchOperationReplace">
    <xpath>Defs/ThingDef[defName="Apparel_PANFluffyMuffler"]/label</xpath>
    <value>
      <label>fluffy muffler</label>
    </value>
  </Operation>










  <Operation Class="PatchOperationAdd">
    <xpath>Defs/ThingDef[defName="Apparel_PAGEyepatchL"]</xpath>
    <value>
    <recipeMaker>
      <researchPrerequisite>ComplexClothing</researchPrerequisite>
      <skillRequirements>
        <Crafting>5</Crafting>
      </skillRequirements>
      <recipeUsers Inherit="False">
        <li>ElectricTailoringBench</li>
        <li>HandTailoringBench</li>
      </recipeUsers>
      <displayPriority>999</displayPriority>
    </recipeMaker>
    </value>
  </Operation>

  <Operation Class="PatchOperationAdd">
    <xpath>Defs/ThingDef[defName="Apparel_PAGEyepatchR"]</xpath>
    <value>
    <recipeMaker>
      <researchPrerequisite>ComplexClothing</researchPrerequisite>
      <skillRequirements>
        <Crafting>5</Crafting>
      </skillRequirements>
      <recipeUsers Inherit="False">
        <li>ElectricTailoringBench</li>
        <li>HandTailoringBench</li>
      </recipeUsers>
      <displayPriority>999</displayPriority>
    </recipeMaker>
    </value>
  </Operation>

  <Operation Class="PatchOperationAdd">
    <xpath>Defs/ThingDef[defName="Apparel_PAGEyepatchLU"]</xpath>
    <value>
    <recipeMaker>
      <researchPrerequisite>ComplexClothing</researchPrerequisite>
      <skillRequirements>
        <Crafting>5</Crafting>
      </skillRequirements>
      <recipeUsers Inherit="False">
        <li>ElectricTailoringBench</li>
        <li>HandTailoringBench</li>
      </recipeUsers>
      <displayPriority>999</displayPriority>
    </recipeMaker>
    </value>
  </Operation>

  <Operation Class="PatchOperationAdd">
    <xpath>Defs/ThingDef[defName="Apparel_PAGEyepatchRU"]</xpath>
    <value>
    <recipeMaker>
      <researchPrerequisite>ComplexClothing</researchPrerequisite>
      <skillRequirements>
        <Crafting>5</Crafting>
      </skillRequirements>
      <recipeUsers Inherit="False">
        <li>ElectricTailoringBench</li>
        <li>HandTailoringBench</li>
      </recipeUsers>
      <displayPriority>999</displayPriority>
    </recipeMaker>
    </value>
  </Operation>


  <Operation Class="PatchOperationAdd">
    <xpath>Defs/ThingDef[defName="Apparel_PAGSunglassesA"]</xpath>
    <value>
    <recipeMaker>
      <researchPrerequisite>ComplexClothing</researchPrerequisite>
      <skillRequirements>
        <Crafting>5</Crafting>
      </skillRequirements>
      <recipeUsers Inherit="False">
        <li>ElectricTailoringBench</li>
        <li>HandTailoringBench</li>
      </recipeUsers>
      <displayPriority>999</displayPriority>
    </recipeMaker>
    </value>
  </Operation>

  <Operation Class="PatchOperationAdd">
    <xpath>Defs/ThingDef[defName="Apparel_PAGSunglassesB"]</xpath>
    <value>
    <recipeMaker>
      <researchPrerequisite>ComplexClothing</researchPrerequisite>
      <skillRequirements>
        <Crafting>5</Crafting>
      </skillRequirements>
      <recipeUsers Inherit="False">
        <li>ElectricTailoringBench</li>
        <li>HandTailoringBench</li>
      </recipeUsers>
      <displayPriority>999</displayPriority>
    </recipeMaker>
    </value>
  </Operation>

  <Operation Class="PatchOperationAdd">
    <xpath>Defs/ThingDef[defName="Apparel_PAGGlasses"]</xpath>
    <value>
    <recipeMaker>
      <researchPrerequisite>ComplexClothing</researchPrerequisite>
      <skillRequirements>
        <Crafting>5</Crafting>
      </skillRequirements>
      <recipeUsers Inherit="False">
        <li>ElectricTailoringBench</li>
        <li>HandTailoringBench</li>
      </recipeUsers>
      <displayPriority>999</displayPriority>
    </recipeMaker>
    </value>
  </Operation>

  <Operation Class="PatchOperationAdd">
    <xpath>Defs/ThingDef[defName="Apparel_PAHCatEarNewsboy"]</xpath>
    <value>
    <recipeMaker>
      <researchPrerequisite>ComplexClothing</researchPrerequisite>
      <skillRequirements>
        <Crafting>5</Crafting>
      </skillRequirements>
      <recipeUsers Inherit="False">
        <li>ElectricTailoringBench</li>
        <li>HandTailoringBench</li>
      </recipeUsers>
      <displayPriority>999</displayPriority>
    </recipeMaker>
    </value>
  </Operation>


  <Operation Class="PatchOperationAdd">
    <xpath>Defs/ThingDef[defName="Apparel_PAHSailorBeret"]</xpath>
    <value>
    <recipeMaker>
      <researchPrerequisite>ComplexClothing</researchPrerequisite>
      <skillRequirements>
        <Crafting>5</Crafting>
      </skillRequirements>
      <recipeUsers Inherit="False">
        <li>ElectricTailoringBench</li>
        <li>HandTailoringBench</li>
      </recipeUsers>
      <displayPriority>999</displayPriority>
    </recipeMaker>
    </value>
  </Operation>

  <Operation Class="PatchOperationAdd">
    <xpath>Defs/ThingDef[defName="Apparel_PAHDeepHood"]</xpath>
    <value>
    <recipeMaker>
      <researchPrerequisite>ComplexClothing</researchPrerequisite>
      <skillRequirements>
        <Crafting>5</Crafting>
      </skillRequirements>
      <recipeUsers Inherit="False">
        <li>ElectricTailoringBench</li>
        <li>HandTailoringBench</li>
      </recipeUsers>
      <displayPriority>999</displayPriority>
    </recipeMaker>
    </value>
  </Operation>

  <Operation Class="PatchOperationAdd">
    <xpath>Defs/ThingDef[defName="Apparel_PAHFedora"]</xpath>
    <value>
    <recipeMaker>
      <researchPrerequisite>ComplexClothing</researchPrerequisite>
      <skillRequirements>
        <Crafting>5</Crafting>
      </skillRequirements>
      <recipeUsers Inherit="False">
        <li>ElectricTailoringBench</li>
        <li>HandTailoringBench</li>
      </recipeUsers>
      <displayPriority>999</displayPriority>
    </recipeMaker>
    </value>
  </Operation>

  <Operation Class="PatchOperationAdd">
    <xpath>Defs/ThingDef[defName="Apparel_PAHFlatCap"]</xpath>
    <value>
    <recipeMaker>
      <researchPrerequisite>ComplexClothing</researchPrerequisite>
      <skillRequirements>
        <Crafting>5</Crafting>
      </skillRequirements>
      <recipeUsers Inherit="False">
        <li>ElectricTailoringBench</li>
        <li>HandTailoringBench</li>
      </recipeUsers>
      <displayPriority>999</displayPriority>
    </recipeMaker>
    </value>
  </Operation>

  <Operation Class="PatchOperationReplace">
    <xpath>Defs/ThingDef[defName="Apparel_PAHHeadScarf"]/recipeMaker</xpath>
    <value>
    <recipeMaker>
      <researchPrerequisite>ComplexClothing</researchPrerequisite>
      <skillRequirements>
        <Crafting>5</Crafting>
      </skillRequirements>
      <recipeUsers Inherit="False">
        <li>ElectricTailoringBench</li>
        <li>HandTailoringBench</li>
      </recipeUsers>
      <displayPriority>999</displayPriority>
    </recipeMaker>
    </value>
  </Operation>

  <Operation Class="PatchOperationReplace">
    <xpath>Defs/ThingDef[defName="Apparel_PAHHalfKitsuneMask"]/recipeMaker</xpath>
    <value>
      <recipeMaker>
        <recipeUsers Inherit="False">
          <li>Ferny_CostumingTable</li>
        </recipeUsers>
        <researchPrerequisite Inherit="False">Ferny_CostumingTable</researchPrerequisite>
      </recipeMaker>
    </value>
  </Operation>



















  <Operation Class="PatchOperationReplace">
    <xpath>Defs/ThingDef[@Name="PAEarringBase"]/recipeMaker</xpath>
    <value>
      <recipeMaker>
        <recipeUsers Inherit="False">
          <li>Ferny_VanityTable</li>
        </recipeUsers>
        <researchPrerequisite Inherit="False">Ferny_VanityTable</researchPrerequisite>
      </recipeMaker>
    </value>
  </Operation>

  <Operation Class="PatchOperationReplace">
    <xpath>Defs/ThingDef[defName="Apparel_PAHHeadScarfB"]/recipeMaker</xpath>
    <value>
      <recipeMaker>
        <recipeUsers Inherit="False">
          <li>Ferny_VanityTable</li>
        </recipeUsers>
        <researchPrerequisite Inherit="False">Ferny_VanityTable</researchPrerequisite>
      </recipeMaker>
    </value>
  </Operation>

  <Operation Class="PatchOperationReplace">
    <xpath>Defs/ThingDef[defName="Apparel_PAHHeadband"]/recipeMaker</xpath>
    <value>
      <recipeMaker>
        <recipeUsers Inherit="False">
          <li>Ferny_VanityTable</li>
        </recipeUsers>
        <researchPrerequisite Inherit="False">Ferny_VanityTable</researchPrerequisite>
      </recipeMaker>
    </value>
  </Operation>

  <Operation Class="PatchOperationReplace">
    <xpath>Defs/ThingDef[defName="Apparel_PAHRibbonHeadband"]/recipeMaker</xpath>
    <value>
      <recipeMaker>
        <recipeUsers Inherit="False">
          <li>Ferny_VanityTable</li>
        </recipeUsers>
        <researchPrerequisite Inherit="False">Ferny_VanityTable</researchPrerequisite>
      </recipeMaker>
    </value>
  </Operation>

  <Operation Class="PatchOperationReplace">
    <xpath>Defs/ThingDef[defName="Apparel_PAHDekaRibbon"]/recipeMaker</xpath>
    <value>
      <recipeMaker>
        <recipeUsers Inherit="False">
          <li>Ferny_VanityTable</li>
        </recipeUsers>
        <researchPrerequisite Inherit="False">Ferny_VanityTable</researchPrerequisite>
      </recipeMaker>
    </value>
  </Operation>

  <Operation Class="PatchOperationReplace">
    <xpath>Defs/ThingDef[defName="Apparel_PAHMokoRibbon"]/recipeMaker</xpath>
    <value>
      <recipeMaker>
        <recipeUsers Inherit="False">
          <li>Ferny_VanityTable</li>
        </recipeUsers>
        <researchPrerequisite Inherit="False">Ferny_VanityTable</researchPrerequisite>
      </recipeMaker>
    </value>
  </Operation>

  <Operation Class="PatchOperationReplace">
    <xpath>Defs/ThingDef[defName="Apparel_PAHHeadphones"]/recipeMaker</xpath>
    <value>
      <recipeMaker>
        <recipeUsers Inherit="False">
          <li>Ferny_VanityTable</li>
        </recipeUsers>
        <researchPrerequisite Inherit="False">Ferny_VanityTable</researchPrerequisite>
      </recipeMaker>
    </value>
  </Operation>

  <Operation Class="PatchOperationReplace">
    <xpath>Defs/ThingDef[defName="Apparel_PAHVeil"]/recipeMaker</xpath>
    <value>
      <recipeMaker>
        <recipeUsers Inherit="False">
          <li>Ferny_VanityTable</li>
        </recipeUsers>
        <researchPrerequisite Inherit="False">Ferny_VanityTable</researchPrerequisite>
      </recipeMaker>
    </value>
  </Operation>

  <Operation Class="PatchOperationReplace">
    <xpath>Defs/ThingDef[defName="Apparel_PAHHeaddress"]/recipeMaker</xpath>
    <value>
      <recipeMaker>
        <recipeUsers Inherit="False">
          <li>Ferny_VanityTable</li>
        </recipeUsers>
        <researchPrerequisite Inherit="False">Ferny_VanityTable</researchPrerequisite>
      </recipeMaker>
    </value>
  </Operation>

  <Operation Class="PatchOperationReplace">
    <xpath>Defs/ThingDef[defName="Apparel_PAHAngolaBeret"]/recipeMaker</xpath>
    <value>
      <recipeMaker>
        <recipeUsers Inherit="False">
          <li>Ferny_VanityTable</li>
        </recipeUsers>
        <researchPrerequisite Inherit="False">Ferny_VanityTable</researchPrerequisite>
      </recipeMaker>
    </value>
  </Operation>

  <Operation Class="PatchOperationReplace">
    <xpath>Defs/ThingDef[defName="Apparel_PAHTiara"]/recipeMaker</xpath>
    <value>
      <recipeMaker>
        <recipeUsers Inherit="False">
          <li>Ferny_VanityTable</li>
        </recipeUsers>
        <researchPrerequisite Inherit="False">Ferny_VanityTable</researchPrerequisite>
      </recipeMaker>
    </value>
  </Operation>

  <Operation Class="PatchOperationReplace">
    <xpath>Defs/ThingDef[defName="Apparel_PAHKnitHeadband"]/recipeMaker</xpath>
    <value>
      <recipeMaker>
        <recipeUsers Inherit="False">
          <li>Ferny_VanityTable</li>
        </recipeUsers>
        <researchPrerequisite Inherit="False">Ferny_VanityTable</researchPrerequisite>
      </recipeMaker>
    </value>
  </Operation>

  <Operation Class="PatchOperationAdd">
    <xpath>Defs/ThingDef[defName="Apparel_PAHPillboxHat"]</xpath>
    <value>
      <recipeMaker>
        <recipeUsers Inherit="False">
          <li>Ferny_VanityTable</li>
        </recipeUsers>
        <researchPrerequisite Inherit="False">Ferny_VanityTable</researchPrerequisite>
      </recipeMaker>
    </value>
  </Operation>


  <Operation Class="PatchOperationReplace">
    <xpath>Defs/ThingDef[defName="Apparel_PAHMechaBunnyEars"]/recipeMaker</xpath>
    <value>
      <recipeMaker>
        <recipeUsers Inherit="False">
          <li>Ferny_VanityTable</li>
        </recipeUsers>
        <researchPrerequisite Inherit="False">Ferny_VanityTable</researchPrerequisite>
      </recipeMaker>
    </value>
  </Operation>

  <Operation Class="PatchOperationReplace">
    <xpath>Defs/ThingDef[defName="Apparel_PAHCyberSunVisor"]/recipeMaker</xpath>
    <value>
      <recipeMaker>
        <recipeUsers Inherit="False">
          <li>Ferny_VanityTable</li>
        </recipeUsers>
        <researchPrerequisite Inherit="False">Ferny_VanityTable</researchPrerequisite>
      </recipeMaker>
    </value>
  </Operation>

  <Operation Class="PatchOperationReplace">
    <xpath>Defs/ThingDef[defName="Apparel_PAHCyberHelm"]/recipeMaker</xpath>
    <value>
      <recipeMaker>
        <recipeUsers Inherit="False">
          <li>Ferny_VanityTable</li>
        </recipeUsers>
        <researchPrerequisite Inherit="False">Ferny_VanityTable</researchPrerequisite>
      </recipeMaker>
    </value>
  </Operation>

  <!-- PAM: force all these to craft ONLY at Ferny_VanityTable + set researchPrerequisite to Ferny_VanityTable -->

  <Operation Class="PatchOperationReplace">
    <xpath>Defs/ThingDef[defName="Apparel_PAMHairExtensions"]/recipeMaker</xpath>
    <value>
      <recipeMaker>
        <recipeUsers Inherit="False">
          <li>Ferny_VanityTable</li>
        </recipeUsers>
        <researchPrerequisite Inherit="False">Ferny_VanityTable</researchPrerequisite>
      </recipeMaker>
    </value>
  </Operation>

  <Operation Class="PatchOperationReplace">
    <xpath>Defs/ThingDef[defName="Apparel_PAMRibbonPin"]/recipeMaker</xpath>
    <value>
      <recipeMaker>
        <recipeUsers Inherit="False">
          <li>Ferny_VanityTable</li>
        </recipeUsers>
        <researchPrerequisite Inherit="False">Ferny_VanityTable</researchPrerequisite>
      </recipeMaker>
    </value>
  </Operation>

  <Operation Class="PatchOperationReplace">
    <xpath>Defs/ThingDef[defName="Apparel_PAMStarHairPin"]/recipeMaker</xpath>
    <value>
      <recipeMaker>
        <recipeUsers Inherit="False">
          <li>Ferny_VanityTable</li>
        </recipeUsers>
        <researchPrerequisite Inherit="False">Ferny_VanityTable</researchPrerequisite>
      </recipeMaker>
    </value>
  </Operation>

  <Operation Class="PatchOperationReplace">
    <xpath>Defs/ThingDef[defName="Apparel_PAMCloverCrown"]/recipeMaker</xpath>
    <value>
      <recipeMaker>
        <recipeUsers Inherit="False">
          <li>Ferny_VanityTable</li>
        </recipeUsers>
        <researchPrerequisite Inherit="False">Ferny_VanityTable</researchPrerequisite>
      </recipeMaker>
    </value>
  </Operation>

  <Operation Class="PatchOperationReplace">
    <xpath>Defs/ThingDef[defName="Apparel_PAMFloralPin"]/recipeMaker</xpath>
    <value>
      <recipeMaker>
        <recipeUsers Inherit="False">
          <li>Ferny_VanityTable</li>
        </recipeUsers>
        <researchPrerequisite Inherit="False">Ferny_VanityTable</researchPrerequisite>
      </recipeMaker>
    </value>
  </Operation>

  <Operation Class="PatchOperationReplace">
    <xpath>Defs/ThingDef[defName="Apparel_PAMRoseCrown"]/recipeMaker</xpath>
    <value>
      <recipeMaker>
        <recipeUsers Inherit="False">
          <li>Ferny_VanityTable</li>
        </recipeUsers>
        <researchPrerequisite Inherit="False">Ferny_VanityTable</researchPrerequisite>
      </recipeMaker>
    </value>
  </Operation>

  <Operation Class="PatchOperationReplace">
    <xpath>Defs/ThingDef[defName="Apparel_PAMPartyHat"]/recipeMaker</xpath>
    <value>
      <recipeMaker>
        <recipeUsers Inherit="False">
          <li>Ferny_VanityTable</li>
        </recipeUsers>
        <researchPrerequisite Inherit="False">Ferny_VanityTable</researchPrerequisite>
      </recipeMaker>
    </value>
  </Operation>

  <!-- PAN: force these to craft ONLY at Ferny_VanityTable + set researchPrerequisite to Ferny_VanityTable -->

  <Operation Class="PatchOperationAdd">
    <xpath>Defs/ThingDef[defName="Apparel_PANMuffler"]</xpath>
    <value>
      <recipeMaker>
        <recipeUsers Inherit="False">
          <li>Ferny_VanityTable</li>
        </recipeUsers>
        <researchPrerequisite Inherit="False">Ferny_VanityTable</researchPrerequisite>
      </recipeMaker>
    </value>
  </Operation>

  <Operation Class="PatchOperationReplace">
    <xpath>Defs/ThingDef[defName="Apparel_PANNeckScarf"]/recipeMaker</xpath>
    <value>
      <recipeMaker>
        <recipeUsers Inherit="False">
          <li>Ferny_VanityTable</li>
        </recipeUsers>
        <researchPrerequisite Inherit="False">Ferny_VanityTable</researchPrerequisite>
      </recipeMaker>
    </value>
  </Operation>

  <Operation Class="PatchOperationReplace">
    <xpath>Defs/ThingDef[defName="Apparel_PANFluffyMuffler"]/recipeMaker</xpath>
    <value>
      <recipeMaker>
        <recipeUsers Inherit="False">
          <li>Ferny_VanityTable</li>
        </recipeUsers>
        <researchPrerequisite Inherit="False">Ferny_VanityTable</researchPrerequisite>
      </recipeMaker>
    </value>
  </Operation>


</Patch>